CGXAssist/CGX.py
CGXAssist/DeviceFinder.py
CGXAssist/__init__.py
CGXAssist/constants.py
CGXAssist-0.0.0.dev0.dist-info/LICENSE
CGXAssist-0.0.0.dev0.dist-info/METADATA
CGXAssist-0.0.0.dev0.dist-info/WHEEL
CGXAssist-0.0.0.dev0.dist-info/top_level.txt
CGXAssist-0.0.0.dev0.dist-info/RECORD
